{
    "studentEssay": [
        {
            "status": "응답대기",
            "FixedDate": "2021-06-01",
            "fixedTime": "30min Ago",
            "title": "why do you want to study in the US?",
            "university": "Harvard University",
            "major": "Computer Science",
            "detail": "I want to study in the US because I want to learn more about computer science and I want to learn from the best professors in the world. I also want to meet new people and experience new things. I think studying in the US will help me achieve my goals and become a better person.I want to study in the US because I want to learn more about computer science and I want to learn from the best professors in the world. I also want to meet new people and experience new things. I think studying in the US will help me achieve my goals and become a better person.I want to study in the US because I want to learn more about computer science and I want to learn from the best professors in the world. I also want to meet new people and experience new things. I think studying in the US will help me achieve my goals and become a better person."
        },
        {
            "status": "응답대기",
            "FixedDate": "2021-06-01",
            "fixedTime": "30min Ago",
            "title": "why do you want to study in the US? why can't you study in Korea?",
            "university": "Harvard University",
            "major": "Computer Science",
            "detail": "I want to study in the US because I want to learn more about computer science and I want to learn from the best professors in the world. I also want to meet new people and experience new things. I think studying in the US will help me achieve my goals and become a better person."
        },
        {
            "status": "응답대기",
            "FixedDate": "2021-06-01",
            "fixedTime": "30min Ago",
            "title": "why do you want to study in the US?",
            "university": "Harvard University",
            "major": "Computer Science",
            "detail": "I want to study in the US because I want to learn more about computer science and I want to learn from the best professors in the world. I also want to meet new people and experience new things. I think studying in the US will help me achieve my goals and become a better person."
        },
        {
            "status": "응답대기",
            "FixedDate": "2021-06-01",
            "fixedTime": "30min Ago",
            "title": "why do you want to study in the US?",
            "university": "Harvard University",
            "major": "Computer Science",
            "detail": "I want to study in the US because I want to learn more about computer science and I want to learn from the best professors in the world. I also want to meet new people and experience new things. I think studying in the US will help me achieve my goals and become a better person."
        },
        {
            "status": "응답대기",
            "FixedDate": "2021-06-01",
            "fixedTime": "30min Ago",
            "title": "why do you want to study in the US?",
            "university": "Harvard University",
            "major": "Computer Science",
            "detail": "I want to study in the US because I want to learn more about computer science and I want to learn from the best professors in the world. I also want to meet new people and experience new things. I think studying in the US will help me achieve my goals and become a better person."
        },
        {
            "status": "응답대기",
            "FixedDate": "2021-06-01",
            "fixedTime": "30min Ago",
            "title": "why do you want to study in the US?",
            "university": "Harvard University",
            "major": "Computer Science",
            "detail": "I want to study in the US because I want to learn more about computer science and I want to learn from the best professors in the world. I also want to meet new people and experience new things. I think studying in the US will help me achieve my goals and become a better person."
        },
        {
            "status": "응답대기",
            "FixedDate": "2021-06-01",
            "fixedTime": "30min Ago",
            "title": "why do you want to study in the US?",
            "university": "Harvard University",
            "major": "Computer Science",
            "detail": "I want to study in the US because I want to learn more about computer science and I want to learn from the best professors in the world. I also want to meet new people and experience new things. I think studying in the US will help me achieve my goals and become a better person."
        },
        {
            "status": "응답대기",
            "FixedDate": "2021-06-01",
            "fixedTime": "30min Ago",
            "title": "why do you want to study in the US?",
            "university": "Harvard University",
            "major": "Computer Science",
            "detail": "I want to study in the US because I want to learn more about computer science and I want to learn from the best professors in the world. I also want to meet new people and experience new things. I think studying in the US will help me achieve my goals and become a better person."
        },
        {
            "status": "응답대기",
            "FixedDate": "2021-06-01",
            "fixedTime": "30min Ago",
            "title": "why do you want to study in the US?",
            "university": "Harvard University",
            "major": "Computer Science",
            "detail": "I want to study in the US because I want to learn more about computer science and I want to learn from the best professors in the world. I also want to meet new people and experience new things. I think studying in the US will help me achieve my goals and become a better person."
        },
        {
            "status": "응답대기",
            "FixedDate": "2021-06-01",
            "fixedTime": "30min Ago",
            "title": "why do you want to study in the US?",
            "university": "Harvard University",
            "major": "Computer Science",
            "detail": "I want to study in the US because I want to learn more about computer science and I want to learn from the best professors in the world. I also want to meet new people and experience new things. I think studying in the US will help me achieve my goals and become a better person."
        },
        {
            "status": "응답대기",
            "FixedDate": "2021-06-01",
            "fixedTime": "30min Ago",
            "title": "why do you want to study in the US?",
            "university": "Harvard University",
            "major": "Computer Science",
            "detail": "I want to study in the US because I want to learn more about computer science and I want to learn from the best professors in the world. I also want to meet new people and experience new things. I think studying in the US will help me achieve my goals and become a better person."
        },
        {
            "status": "응답대기",
            "FixedDate": "2021-06-01",
            "fixedTime": "30min Ago",
            "title": "why do you want to study in the US?",
            "university": "Harvard University",
            "major": "Computer Science",
            "detail": "I want to study in the US because I want to learn more about computer science and I want to learn from the best professors in the world. I also want to meet new people and experience new things. I think studying in the US will help me achieve my goals and become a better person."
        }
    ]
}